try_py_poerty/__init__.py
try_py_poerty/main.py
try_py_poerty-0.1.0.dist-info/METADATA
try_py_poerty-0.1.0.dist-info/WHEEL
try_py_poerty-0.1.0.dist-info/RECORD
